lulu/__init__.py
lulu/__main__.py
lulu/common.py
lulu/config.py
lulu/extractor.py
lulu/json_output.py
lulu/version.py
lulu/cli_wrapper/__init__.py
lulu/cli_wrapper/downloader/__init__.py
lulu/cli_wrapper/openssl/__init__.py
lulu/cli_wrapper/player/__init__.py
lulu/cli_wrapper/player/__main__.py
lulu/cli_wrapper/player/dragonplayer.py
lulu/cli_wrapper/player/gnome_mplayer.py
lulu/cli_wrapper/player/mplayer.py
lulu/cli_wrapper/player/vlc.py
lulu/cli_wrapper/player/wmp.py
lulu/cli_wrapper/transcoder/__init__.py
lulu/cli_wrapper/transcoder/ffmpeg.py
lulu/cli_wrapper/transcoder/libav.py
lulu/cli_wrapper/transcoder/mencoder.py
lulu/extractors/__init__.py
lulu/extractors/acfun.py
lulu/extractors/alive.py
lulu/extractors/archive.py
lulu/extractors/baidu.py
lulu/extractors/bandcamp.py
lulu/extractors/baomihua.py
lulu/extractors/bcy.py
lulu/extractors/bigthink.py
lulu/extractors/bilibili.py
lulu/extractors/bokecc.py
lulu/extractors/cbs.py
lulu/extractors/ckplayer.py
lulu/extractors/cntv.py
lulu/extractors/coub.py
lulu/extractors/dailymotion.py
lulu/extractors/dilidili.py
lulu/extractors/douban.py
lulu/extractors/douyin.py
lulu/extractors/douyutv.py
lulu/extractors/ehow.py
lulu/extractors/embed.py
lulu/extractors/facebook.py
lulu/extractors/fantasy.py
lulu/extractors/fc2video.py
lulu/extractors/flickr.py
lulu/extractors/freesound.py
lulu/extractors/funshion.py
lulu/extractors/giphy.py
lulu/extractors/google.py
lulu/extractors/heavymusic.py
lulu/extractors/huaban.py
lulu/extractors/huomaotv.py
lulu/extractors/icourses.py
lulu/extractors/ifeng.py
lulu/extractors/imgur.py
lulu/extractors/infoq.py
lulu/extractors/instagram.py
lulu/extractors/interest.py
lulu/extractors/iqilu.py
lulu/extractors/iqiyi.py
lulu/extractors/iwara.py
lulu/extractors/ixigua.py
lulu/extractors/joy.py
lulu/extractors/khan.py
lulu/extractors/ku6.py
lulu/extractors/kuaishou.py
lulu/extractors/kugou.py
lulu/extractors/kuwo.py
lulu-0.5.3.dist-info/DESCRIPTION.rst
lulu-0.5.3.dist-info/METADATA
lulu-0.5.3.dist-info/RECORD
lulu-0.5.3.dist-info/WHEEL
lulu-0.5.3.dist-info/entry_points.txt
lulu-0.5.3.dist-info/metadata.json
lulu-0.5.3.dist-info/top_level.txt
