Metadata-Version: 2.0
Name: lulu
Version: 0.5.3
Summary: A simple and clean video/music/image downloader that supports many websites 👾
Home-page: https://github.com/iawia002/Lulu
Author: iawia002
Author-email: z2d@jifangcheng.com
License: MIT
Platform: UNKNOWN
Classifier: License :: OSI Approved :: MIT License
Classifier: Programming Language :: Python
Classifier: Programming Language :: Python :: 3
Classifier: Programming Language :: Python :: 3 :: Only
Classifier: Programming Language :: Python :: 3.4
Classifier: Programming Language :: Python :: 3.5
Classifier: Programming Language :: Python :: 3.6
Classifier: Programming Language :: Python :: Implementation :: CPython
Requires-Dist: cryptography (==2.1.4)
Requires-Dist: beautifulsoup4 (==4.6.0)
Requires-Dist: requests (==2.18.4)
